modelbase_pde/__init__.py
modelbase_pde/basemodels.py
modelbase_pde/leafmodels.py
modelbase_pde/utils/__init__.py
modelbase_pde/utils/coordinates.py
modelbase_pde/utils/perffuncs.cpp
modelbase_pde/utils/perffuncs.py
modelbase_pde/utils/plotting.py
modelbase_pde/utils/_perffuncs.cpython-310-x86_64-linux-gnu.so
modelbase_pde-0.2.46.dist-info/LICENSE
modelbase_pde-0.2.46.dist-info/WHEEL
modelbase_pde-0.2.46.dist-info/METADATA
modelbase_pde-0.2.46.dist-info/RECORD
