Metadata-Version: 2.1
Name: modelbase-pde
Version: 0.2.46
Summary: A subpackage of modelbase that enables investigation of PDE models
Author: Marvin van Aalst
Author-email: marvin.vanaalst@gmail.com
Requires-Python: >=3.8,<4.0
Classifier: Programming Language :: Python :: 3
Classifier: Programming Language :: Python :: 3.8
Classifier: Programming Language :: Python :: 3.9
Classifier: Programming Language :: Python :: 3.10
Classifier: Programming Language :: Python :: 3.11
Requires-Dist: modelbase (>=1.18.9,<2.0.0)
Requires-Dist: pybind11 (>=2.10.0,<3.0.0)
Requires-Dist: setuptools (>=65.4.0,<66.0.0)
